<?xml version="1.0" encoding="UTF-8"?>
<odoo>
    <menuitem id="test_menu_root" name="Real Estate">
        <menuitem id="property_menu" name="Property">
            <menuitem id="property_list_menu_action" action="property_list_action"/>
        </menuitem>
        <menuitem id="setting_menu" name="Setting">
            <menuitem id="setting_menu_action1" action="setting_action1"/>
            <menuitem id="setting_menu_action2" action="setting_action2"/>
        </menuitem>
    </menuitem>
</odoo>
